mycalc/claculator.py
Mycalc2024qq-0.0.2.dist-info/METADATA
Mycalc2024qq-0.0.2.dist-info/WHEEL
Mycalc2024qq-0.0.2.dist-info/top_level.txt
Mycalc2024qq-0.0.2.dist-info/RECORD
