Metadata-Version: 2.1
Name: Mycalc2024qq
Version: 0.0.2
Summary: nice calculator
Home-page: https://github.com/jhb113/cacl0001
Download-URL: https://github.com/jhb113/cacl0001
Author: Hyunbin
Classifier: Programming Language :: Python :: 3
